polymer_visual/__init__.py
polymer_visual/api.py
polymer_visual/main.py
polymer_visual/plots/__init__.py
polymer_visual/plots/base.py
polymer_visual/plots/composite.py
polymer_visual/plots/contour.py
polymer_visual/plots/individual.py
polymer_visual/plots/line.py
polymer_visual/plots/scattering.py
polymer_visual/readers/__init__.py
polymer_visual/readers/rgrid_reader.py
polymer_visual/utils/__init__.py
polymer_visual/utils/basis.py
polymer_visual/utils/colormaps.py
polymer_visual/utils/isovalues.py
polymer_visual-1.0.0.dist-info/METADATA
polymer_visual-1.0.0.dist-info/WHEEL
polymer_visual-1.0.0.dist-info/entry_points.txt
polymer_visual-1.0.0.dist-info/RECORD
