Metadata-Version: 2.4
Name: polymer-visual
Version: 1.0.0
Summary: Visualization tools for polymer self-assembly simulation data (SCFT/PSCF)
License: MIT
Keywords: polymer,scft,visualization,scientific,simulation
Author: Original MATLAB code by Naveen Pillai, Akash Arora, Ben Magruder
Requires-Python: >=3.8,<4.0
Classifier: Development Status :: 4 - Beta
Classifier: Intended Audience :: Science/Research
Classifier: License :: OSI Approved :: MIT License
Classifier: Operating System :: OS Independent
Classifier: Programming Language :: Python :: 3
Classifier: Programming Language :: Python :: 3.8
Classifier: Programming Language :: Python :: 3.9
Classifier: Programming Language :: Python :: 3.10
Classifier: Programming Language :: Python :: 3.11
Classifier: Programming Language :: Python :: 3.12
Classifier: Programming Language :: Python :: 3.13
Classifier: Programming Language :: Python :: 3.14
Classifier: Topic :: Scientific/Engineering :: Visualization
Provides-Extra: png
Requires-Dist: click (>=8.1.0,<9.0.0)
Requires-Dist: kaleido (>=0.2.1,<0.3.0) ; extra == "png"
Requires-Dist: matplotlib (>=3.7.0,<4.0.0)
Requires-Dist: numpy (>=1.24.0,<2.0.0)
Requires-Dist: packaging (>=23.0,<24.0)
Requires-Dist: plotly (>=5.15.0)
Requires-Dist: scipy (>=1.10.0,<2.0.0)
Project-URL: Documentation, https://github.com/kdorfmanUMN/polymer_visual#readme
Project-URL: Homepage, https://github.com/kdorfmanUMN/polymer_visual
Project-URL: Repository, https://github.com/kdorfmanUMN/polymer_visual
